bakery/__init__.py
bakery/bakery.py
bakery/bakery.pyi
bakery/baking.py
bakery/cake.py
bakery/mypy.py
bakery/piece_of_cake.py
bakery/py.typed
bakery/stuff/__init__.py
bakery/stuff/cake_stuff.py
bakery/stuff/log_stuff.py
bakery/stuff/stuff.py
bakery/stuff/types.py
bakery/testbakery.py
fresh_bakery-0.4.3.dist-info/LICENSE
fresh_bakery-0.4.3.dist-info/METADATA
fresh_bakery-0.4.3.dist-info/WHEEL
fresh_bakery-0.4.3.dist-info/entry_points.txt
fresh_bakery-0.4.3.dist-info/RECORD
