Metadata-Version: 2.3
Name: fresh-bakery
Version: 0.4.3
Summary: Bake your dependencies stupidly simple!
License: MIT
Keywords: Dependency Injection,Dependency Injection pattern,Constructor Injection,Inversion of Control,Inversion of Control Container,IoC
Author: Dmitry Makarov
Author-email: mit.makaroff@gmail.com
Requires-Python: >=3.8,<3.14
Classifier: Intended Audience :: Developers
Classifier: License :: OSI Approved :: MIT License
Classifier: Operating System :: OS Independent
Classifier: Programming Language :: Python :: 3
Classifier: Programming Language :: Python :: 3.8
Classifier: Programming Language :: Python :: 3.9
Classifier: Programming Language :: Python :: 3.10
Classifier: Programming Language :: Python :: 3.11
Classifier: Programming Language :: Python :: 3.12
Classifier: Programming Language :: Python :: 3.13
Classifier: Topic :: Software Development
Classifier: Topic :: Software Development :: Libraries
Classifier: Topic :: Software Development :: Libraries :: Python Modules
Project-URL: Changelog, https://github.com/Mityuha/fresh-bakery/releases
Project-URL: Documentation, https://fresh-bakery.readthedocs.io/en/latest/
Project-URL: Source, https://github.com/Mityuha/fresh-bakery
Project-URL: Tracker, https://github.com/Mityuha/fresh-bakery/issues
